dragoncurses/README.md
dragoncurses/__init__.py
dragoncurses/component.py
dragoncurses/context.py
dragoncurses/input.py
dragoncurses/loop.py
dragoncurses/py.typed
dragoncurses/scene.py
dragoncurses/settings.py
dragoncurses-0.2.1.dist-info/LICENSE
dragoncurses-0.2.1.dist-info/METADATA
dragoncurses-0.2.1.dist-info/WHEEL
dragoncurses-0.2.1.dist-info/top_level.txt
dragoncurses-0.2.1.dist-info/RECORD
