Metadata-Version: 2.1
Name: dragoncurses
Version: 0.2.1
Summary: Console-based UI toolkit building on top of curses.
Home-page: https://github.com/DragonMinded/dragoncurses
Author: DragonMinded
Author-email: dragonminded@dragonminded.com
License: Public Domain
Requires-Python: >=3.6
License-File: LICENSE
Requires-Dist: windows-curses ; platform_system == "Windows"
